nwp/__init__.py
nwp/icon/__init__.py
nwp/icon/app.py
nwp/icon/consts.py
nwp/icon/utils.py
nwp/metoffice/__init__.py
tests/__init__.py
nwp-0.0.1.dist-info/LICENSE
nwp-0.0.1.dist-info/METADATA
nwp-0.0.1.dist-info/WHEEL
nwp-0.0.1.dist-info/top_level.txt
nwp-0.0.1.dist-info/RECORD
