Metadata-Version: 2.1
Name: nwp
Version: 0.0.1
Summary: NWP Processing
Author: Jack Kelly, Peter Dudfield, Jacob Bieker
Author-email: info@openclimatefix.org
License: MIT
License-File: LICENSE
